[
    {
        "name": "mini tank",
        "category": "Котловые насосы",
        "short_description": "Новый усовершенствованный наливной насос модели Mini Tank можно устанавливать на стене, на полу, в поддоне или осуществлять подвесной монтаж на шпильке M8/M10. Благодаря применению поршневой технологии он является компактным, мощным и многофункциональным наливным насосом.",
        "image": "https://aspenpumps.com/sites/default/files/styles/max_width_1600/public/2017-10/MiniTank.jpg?itok=2Iz1KUal",
        "killer_features": [
            "макс. производительность 35Л/ч",
            "макс. реком. высота подъема 15M",
            "35дБ(А)"
        ],
        "description": "<h2>ОСОБЕННОСТИ</h2><ul><li>Четыре варианта установки</li><li>Компактный и неброский</li><li>Возможность размещения в сливном поддоне</li><li>Простота техобслуживания</li></ul><h2>ПРИМЕНЕНИЕ</h2><ul><li>До 46 кВт / 157000 БТЕ/ч</li><li>Канальные и кассетные кондиционеры; напольные или устанавливаемые на шасси кондиционеры.</li><li>Идеально подходят для... гибкого монтажа</li></ul>",
        "specifications": {
            "Макс  производительность": "35Л/ч",
            "Емкость резервуара": "0.24L",
            "Электропитание": "230 В перем. тока, 50–60 Гц, 0,1 A*",
            "класс": "изоляции II",
            "Макс  температура воды": "40°C / 104°F",
            "выход": "Трубка с внутр. диам. 6 и 10 мм",
            "Выключатель-предохранитель": "на 3,0 А Н.З.",
            "Полная герметизация": "Да",
            "Part number": "FP1056/2",
            "Макс  реком  высота подъема": "15M",
            "уровень шума на расстоянии 1 м": "35дБ(А)",
            "Режим работы": "Прерывистый",
            "мощность": "46 кВт / 157000 БТЕ/ч",
            "Вход": "2 отв. диам. 22 мм, 1 отв. диам. 12 мм и 27 мм",
            "Степень защиты": "IPX65",
            "Тепловая защита": "Да",
            "Самовсасывание": "n/a"
        }
    },

    {
        "name": "MAX Hi-Flow",
        "category": "Баковые насосы",
        "image": "https://aspenpumps.com/sites/default/files/styles/max_width_1600/public/2017-11/MaxHighFlow_03.jpg?itok=Ic0LJZ-l",
        "short_description": "Это лучший в своем классе насос Max Hi-Flow, сочетающий в себе традиционную технологию сборки и высокую производительность Aspen Pumps. С наименьшим уровнем шума dB (A) и наилучшим классом защиты IP (защита от брызг IP24) для всех наливных насосов Max Hi-Flow является самым малошумным и надежным насосом в данном классе.",
        "killer_features": [
            "макс. производительность: 550Л/ч",
            "макс. реком. высота подъема 5M",
            "44дБ(А)"
        ],
        "description": "<h2>ОСОБЕННОСТИ</h2><ul><li>IP24 – Брызгозащищенный</li><li>Простой доступ к резервуару</li><li>Встроенный спиртовой уровень</li><li>Технология Plug & play</li></ul><h2>ПРИМЕНЕНИЕ</h2><ul><li>До 733 кВт / 2.5 млн. БТЕ/ч</li><li>Канальные и кассетные, напольные или устанавливаемые на шасси кондиционеры</li></ul>",
        "specifications": {
            "Макс производительность": "550Л/ч",
            "Емкость резервуара": "1.7L",
            "Электропитание": "230 В перем. тока, 50 Гц, 0,8 A*",
            "класс": "изоляции I",
            "Макс температура воды": "40°C / 104°F",
            "выход": "Трубка с внутр. диам. 6 и 10 мм",
            "Выключатель-предохранитель": "на 3,0 А Н.З.",
            "Полная герметизация": "n/a",
            "Part number": "FP3349",
            "Макс реком высота подъема": "5M",
            "уровень шума на расстоянии 1 м": "44дБ(А)",
            "Режим работы": "Прерывистый",
            "мощность": "733 кВт / 2.5 M БТЕ/ч",
            "Вход": "4 отв. диам. 21 мм и 27 мм",
            "Степень защиты": "IPX24",
            "Тепловая защита": "Да",
            "Самовсасывание": "n/a"
        }
    },

    {
        "name": "hi-lift 1L & 2L",
        "category": "Котловые насосы",
        "short_description": "Единственный в мире перистальтический наливной насос гарантирует непревзойденно высокую высоту подъема и не имеющую себе равных надежность работы.",
        "image": "https://aspenpumps.com/sites/default/files/styles/max_width_1600/public/2017-11/HiLift.jpg?itok=EVXVVzQB",
        "killer_features": [
            "макс. производительность 11Л/ч",
            "макс. реком. высота подъема 12M",
            "51дБ(А)"
        ],
        "description": "<h2>ОСОБЕННОСТИ</h2> <ul> <li>Значительная высота подъема</li> <li>Простота установки и техобслуживания</li> <li>Простота доступа к резервуару</li> <li>Встроенный спиртовой уровень</li> </ul> <h2>ПРИМЕНЕНИЕ</h2> <ul> <li>До 14 кВт / 47000 БТЕ/ч</li> <li>Канальные и кассетные кондиционеры; напольные или устанавливаемые на шасси кондиционеры; холодильные шкафы и камеры.</li> </ul>",
        "specifications": {
            "Макс производительность": "11Л/ч",
            "Емкость резервуара": "1L / 2L",
            "Электропитание": "230 В перем.тока 50-60 Гц 0.4A*",
            "класс": "изоляции I",
            "Макс температура воды": "40°C / 104°F",
            "выход": "1 вых. отверстие диаметром 6 мм",
            "Выключатель-предохранитель": "на 3,0 А Н.З.",
            "Полная герметизация": "n/a",
            "Макс реком высота подъема": "12M",
            "уровень шума на расстоянии 1 м": "51дБ(А)",
            "Режим работы": "непрерывный",
            "мощность": "14 кВт / 47000 БТЕ/ч",
            "Вход": "3 вх. отверстия диаметром 25 мм",
            "Степень защиты": "IPX0",
            "Тепловая защита": "Да",
            "Самовсасывание": "n/a"
        }
    },

    {
        "name": "heavy duty 6",
        "category": "Котловые насосы",
        "short_description": "Эти прочные и надежные насосы модельного ряда Heavy Duty обладают впечатляющей производительностью и идеально подходят для быстрого отвода больших объемов конденсата.",
        "image": "https://aspenpumps.com/sites/default/files/styles/max_width_1600/public/2017-11/HeavyDuty10m.jpg?itok=CJ6OICpq",
        "killer_features": [
            "макс. производительность 900Л/ч",
            "макс. реком. высота подъема 6M",
            "60дБ(А)"
        ],
        "description": "<h2>ОСОБЕННОСТИ</h2> <ul> <li>Высокая производительность</li> <li>Обратный клапан</li> <li>Простота установки</li> <li>Емкость резервуара 4 л</li> </ul> <h2>ПРИМЕНЕНИЕ</h2> <ul> <li>6: До 1200 кВт / 4 млн. БТЕ/ч</li> <li>Холодильные витрины; увлажнители; установки для подготовки воздуха (AHU)</li> </ul>",
        "specifications": {
            "Макс производительность": "900Л/ч",
            "Емкость резервуара": "4L",
            "Электропитание": "230 VAC, 1.5A, 50Hz",
            "класс": "изоляции I",
            "Макс температура воды": "40°C / 104°F",
            "выход": "10mm",
            "Выключатель-предохранитель": "3.0A Normally closed",
            "Полная герметизация": "n/a",
            "Part number": "FP2074/2",
            "Макс реком высота подъема": "6M",
            "уровень шума на расстоянии 1 м": "60дБ(А)",
            "Режим работы": "Прерывистый",
            "мощность": "1200kW / 4m Btu/h",
            "Вход": "x2 40mm",
            "Степень защиты": "IPX20",
            "Самовсасывание": "n/a"
        }
    },

    {
        "name": "heavy duty 10",
        "category": "Котловые насосы",
        "short_description": "Эти прочные и надежные насосы модельного ряда Heavy Duty обладают впечатляющей производительностью и идеально подходят для быстрого отвода больших объемов конденсата.",
        "image": "https://aspenpumps.com/sites/default/files/styles/max_width_1600/public/2017-11/HeavyDuty10m.jpg?itok=CJ6OICpq",
        "killer_features": [
            "макс. производительность 1070Л/ч",
            "макс. реком. высота подъема 9M",
            "64дБ(А)"
        ],
        "description": "<h2>ОСОБЕННОСТИ</h2> <ul> <li>Высокая производительность</li> <li>Обратный клапан</li> <li>Простота установки</li> <li>Емкость резервуара 4 л</li> </ul> <h2>ПРИМЕНЕНИЕ</h2> <ul> <li>HD10: До 1460 кВт / 4,9 млн. БТЕ/ч</li> <li>Холодильные витрины; увлажнители; установки для подготовки воздуха (AHU)</li> </ul>",
        "specifications": {
            "Макс производительность": "1070Л/ч",
            "Емкость резервуара": "4L",
            "Электропитание": "230 В перем. тока 50–60 Гц 0,38 А",
            "класс": "изоляции I",
            "Макс температура воды": "40°C / 104°F",
            "выход": " 1 вых. отверстие диаметром 10 мм",
            "Выключатель-предохранитель": "на 4,0 А Н.З.",
            "Полная герметизация": "n/a",
            "Part number": "FP2066/2",
            "Макс реком высота подъема": "9M",
            "уровень шума на расстоянии 1 м": "64дБ(А)",
            "Режим работы": "Прерывистый",
            "мощность": "460 кВт / 4,9 млн БТЕ/ч",
            "Вход": "2 вх. отверстия диаметром 40 мм",
            "Степень защиты": "IPX0",
            "Самовсасывание": "n/a"
        }
    },

    {
        "name": "hot water economy",
        "category": "Котловые насосы",
        "short_description": "Этот экономичный насос, изготовленный из термостойкого материала Cycoloy, предназначен для отвода воды с высокой температурой.",
        "image": "https://aspenpumps.com/sites/default/files/styles/max_width_1600/public/2017-11/HotWaterEconomy.jpg?itok=nYosqJ7V",
        "killer_features": [
            "макс. производительность 900Л/ч",
            "макс. реком. высота подъема 7M",
            "60дБ(А)"
        ],
        "description": "<h2>ОСОБЕННОСТИ</h2> <ul> <li>Высокая производительность</li> <li>Отводит воду, нагретую до 80 °C</li> <li>2 входных отверстия</li> </ul> <h2>ПРИМЕНЕНИЕ</h2> <ul> <li>До 1200 кВт / 4 млн. БТЕ/ч</li> <li>Увлажнители; котлы; холодильные установки; установки для подготовки воздуха (AHU)</li> </ul>",
        "specifications": {
            "Макс производительность": "900Л/ч",
            "Емкость резервуара": "4L",
            "Электропитание": "230 В перем.тока 50 Гц 1,5A",
            "класс": "изоляции I",
            "Макс температура воды": "100 °C / 212°F",
            "выход": "1 вых. отверстие диаметром 10 мм",
            "Выключатель-предохранитель": "на 3,0 А Н.З",
            "Полная герметизация": "n/a",
            "Part number": "FP2092/2",
            "Макс реком высота подъема": "7M",
            "уровень шума на расстоянии 1 м": "60дБ(А)",
            "Режим работы": "Прерывистый",
            "мощность": "230 В перем.тока 50 Гц 1,5A",
            "Вход": "2 вх. отверстия диаметром 40 мм",
            "Степень защиты": "IPX20",
            "Тепловая защита": "Да",
            "Самовсасывание": "n/a"
        }
    },

    {
        "name": "hot water heavy duty",
        "category": "Котловые насосы",
        "short_description": "Превосходный насос модели Hot Water Heavy Duty предназначен для отвода воды с температурой 80°C и обеспечивает потрясающее значение производительности1800 л/ч — больше нет слишком тяжелой работы!",
        "image": "https://aspenpumps.com/sites/default/files/styles/max_width_1600/public/2017-11/HotWaterHDuty.jpg?itok=dL3we5eO",
        "killer_features": [
            "макс. производительность 1800Л/ч",
            "макс. реком. высота подъема 15M",
            "63дБ(А)"
        ],
        "description": "<h2>ОСОБЕННОСТИ</h2> <ul> <li>Значительная высота подъема</li> <li>Обрабатывает воду, нагретую до 80 °C</li> <li>Обратный клапан</li> <li>Простота установки</li> </ul> <h2>ПРИМЕНЕНИЕ</h2> <ul> <li>До 2400 кВт / 8 млн. БТЕ/ч</li> <li>Установки для подготовки воздуха (AHU); увлажнители; котлы; холодильные установки</li> </ul>",
        "specifications": {
            "Макс производительность": "1800Л/ч",
            "Емкость резервуара": "5L",
            "Электропитание": "230 В перем.тока 50 Гц 1,5A",
            "класс": "изоляции I",
            "Макс температура воды": "80 °C / 176°F",
            "выход": "1 вых. отверстие диаметром 15 мм",
            "Выключатель-предохранитель": "на 4,0 А Н.З",
            "Полная герметизация": "n/a",
            "Part number": "FP2132",
            "Макс реком высота подъема": "15M",
            "уровень шума на расстоянии 1 м": "63дБ(А)",
            "Режим работы": "Непрерывный",
            "мощность": "2400kW",
            "Вход": "2 вх. отверстия диаметром 40 мм",
            "Степень защиты": "IPX1",
            "Тепловая защита": "Да",
            "Самовсасывание": "n/a"
        }
    },

    {
        "name": "low profile errp",
        "category": "Насосы для супермаркетов",
        "short_description": "Низкопрофильный насос ERRP (Economical Retail Refrigeration Pump — экономичный насос для холодильных установок, используемых в розничной торговле) в пластмассовом корпусе предназначен для монтажа исключительно под холодильными витринами и обеспечивает отвод воды, образующейся при размораживании, а также загрязненной воды",
        "image": "https://aspenpumps.com/sites/default/files/styles/max_width_1600/public/2017-10/LowERRP.jpg?itok=8Gijb1go",
        "killer_features": [
            "макс. производительность 190Л/ч",
            "макс. реком. высота подъема 21M",
            "60дБ(А)"
        ],
        "description": "<h2>ОСОБЕННОСТИ</h2> <ul> <li>Небольшой вес и высота</li> <li>Простота очистки и переноски</li> <li>Фильтр для улавливания загрязнений</li> <li>Съемный кабель электропитания</li> </ul> <h2>ПРИМЕНЕНИЕ</h2> <ul> <li>Холодильные установки; холодильные витрины</li> </ul>",
        "specifications": {
            "Макс производительность": "190Л/ч",
            "Емкость резервуара": "3.5L",
            "Электропитание": "230 В перем. тока 50–60 Гц 0,2 A",
            "класс": "изоляции I",
            "Макс температура воды": "40°C / 104°F",
            "выход": "10 мм",
            "Выключатель-предохранитель": "на 3,0 А Н.З",
            "Полная герметизация": "n/a",
            "Part number": "Low Profile ERRP – top inlet FP2597 | Low Profile ERRP – side inlet FP2805",
            "Макс реком высота подъема": "21M",
            "уровень шума на расстоянии 1 м": "60дБ(А)",
            "Режим работы": "Прерывистый",
            "мощность": "n/a",
            "Вход": "50мм",
            "Степень защиты": "IPX4",
            "Тепловая защита": "Да",
            "Самовсасывание": "n/a"
        }
    },

    {
        "name": "errp",
        "category": "Насосы для супермаркетов",
        "short_description": "Стандартный насос ERRP (Economical Retail Refrigeration Pump — экономичный насос для холодильных установок, используемых в розничной торговле), изготовленный из прочной пластмассы, эффективно откачивает воду, которая образуется при размораживании, а также фильтрует загрязнения.",
        "image": "https://aspenpumps.com/sites/default/files/styles/max_width_1600/public/2017-10/ERRP.jpg?itok=5bleJndP",
        "killer_features": [
            "макс производительность 225Л/ч",
            "макс реком высота подъема 35M",
            "60дБ(А)"
        ],
        "description": "<h2>ОСОБЕННОСТИ</h2> <ul> <li>Возможно исполнение с верхним и боковым входными отверстиями</li> <li>Легкий для чистки и переноски</li> <li>Фильтр для улавливания загрязнений</li> <li>Съемный кабель электропитания</li> </ul> <h2>ПРИМЕНЕНИЕ</h2> <ul> <li>Холодильные установки; холодильные витрины</li> <li>Идеально подходят для... нескольких холодильных агрегатов</li> </ul>",
        "specifications": {
            "Макс производительность": "225Л/ч",
            "Емкость резервуара": "11L",
            "Электропитание": "230 В перем. тока 50–60 Гц 0,2 A",
            "класс": "изоляции I",
            "Макс температура воды": "40°C / 104°F",
            "выход": "10 мм",
            "Выключатель-предохранитель": "на 3,0 А Н.З",
            "Полная герметизация": "n/a",
            "Part number": "ERRP – top inlet FP2318 | ERRP – side inlet FP2320",
            "Макс реком высота подъема": "35M",
            "уровень шума на расстоянии 1 м": "60дБ(А)",
            "Режим работы": "Прерывистый",
            "мощность": "n/a",
            "Вход": "50мм",
            "Степень защиты": "IPX24",
            "Тепловая защита": "Да",
            "Самовсасывание": "n/a"
        }
    },

    {
        "name": "cold cabinet",
        "category": "Насосы для супермаркетов",
        "short_description": "Превосходный насос для холодильных установок в прочном корпусе из нержавеющей стали. Предназначенный для монтажа под холодильными агрегатами, он откачивает воду, которая образуется при размораживании и фильтрует загрязнения.",
        "image": "https://aspenpumps.com/sites/default/files/styles/max_width_1600/public/2017-10/ColdCabinet.jpg?itok=gE64Z3YS",
        "killer_features": [
            "макс. производительность 225Л/ч",
            "макс. реком. высота подъема 35M",
            "60дБ(А)"
        ],
        "description": "<h2>ОСОБЕННОСТИ</h2> <ul> <li>Возможно исполнение с верхним и боковым входными отверстиями</li> <li>Большой резервуар</li> <li>Корпус из нержавеющей стали</li> <li>Концепция Plug-and-play</li> </ul> <h2>ПРИМЕНЕНИЕ</h2> <ul> <li>Один или несколько холодильных агрегатов, в составе комплексного оборудования</li> <li>Идеально подходят для... нескольких холодильных агрегатов</li> </ul>",
        "specifications": {
            "Макс производительность": "225Л/ч",
            "Емкость резервуара": "11L",
            "Электропитание": "230 В перем. тока 50–60 Гц 0,38 А",
            "класс": "изоляции I",
            "Макс температура воды": "40°C / 104°F",
            "выход": "10 мм",
            "Выключатель-предохранитель": "на 3,0 А Н.З",
            "Полная герметизация": "n/a",
            "Part number": "Cold Cabinet – top inlet FP2119 | Cold Cabinet – side inlet FP2120",
            "Макс реком высота подъема": "35M",
            "уровень шума на расстоянии 1 м": "60дБ(А)",
            "Режим работы": "Прерывистый",
            "мощность": "n/a",
            "Вход": "50мм",
            "Степень защиты": "IPX1",
            "Тепловая защита": "Да",
            "Самовсасывание": "n/a"
        }
    },

    {
        "name": "macerator 4 л и 10 л",
        "category": "Насосы для супермаркетов",
        "short_description": "Предназначен для сбора воды, образующейся при размораживании нескольких холодильных витрин. Внутренний фильтр с лезвиями предотвращает засорение насоса, что позволяет увеличить временные интервалы между техосмотрами.",
        "image": "https://aspenpumps.com/sites/default/files/styles/max_width_1600/public/2017-11/Macerator10LHR.jpg?itok=I9dW2fzP",
        "killer_features": [
            "макс. производительность 780Л/ч",
            "макс. реком. высота подъема 8.5M",
            "64дБ(А)"
        ],
        "description": "<h2>ОСОБЕННОСТИ</h2> <ul> <li>Фильтр с лезвиями</li> <li>Высокая производительность и высота подъема</li> <li>Выключатель-защита от перелива</li> </ul> <h2>ПРИМЕНЕНИЕ</h2> <ul> <li>Один или несколько холодильных агрегатов</li> <li> Идеально подходят для... размельчения остатков продуктов питания, которые могут попасть в насос/</li> </ul>",
        "specifications": {
            "Макс производительность": "780Л/ч",
            "Емкость резервуара": "4L / 10L",
            "Электропитание": "230 VAC, 0.38A, 50/60Hz",
            "класс": "изоляции I",
            "Макс температура воды": "40°C / 104°F",
            "выход": "10 mm",
            "Выключатель-предохранитель": "4.0A Normally closed",
            "Полная герметизация": "n/a",
            "Part number": "Macerator 4L FP2305 | Macerator 10L FP2307",
            "Макс реком высота подъема": "8.5M",
            "уровень шума на расстоянии 1 м": "64дБ(А)",
            "Режим работы": "Прерывистый",
            "мощность": "n/a",
            "Вход": "x2 40 & 55mm",
            "Степень защиты": "IPX21",
            "Тепловая защита": "Да",
            "Самовсасывание": "n/a",
            "Additional inlet": "3/4” in tank (10L only)"
        }
    }
]
